styxgraph/__init__.py
styxgraph-0.5.2.dist-info/WHEEL
styxgraph-0.5.2.dist-info/METADATA
styxgraph-0.5.2.dist-info/RECORD
