Metadata-Version: 2.4
Name: styxgraph
Version: 0.5.2
Summary: Execution graph middleware for Styx
Author: Florian Rupprecht
Author-email: Florian Rupprecht <33600480+nx10@users.noreply.github.com>
License-Expression: MIT
Requires-Dist: styxdefs>=0.5.0,<0.6
Requires-Python: >=3.10
